discord_markdown_ast_parser/__init__.py
discord_markdown_ast_parser/lexer.py
discord_markdown_ast_parser/parser.py
discord_markdown_ast_parser/shit.txt
discord_markdown_ast_parser-1.0.6.dist-info/LICENSE
discord_markdown_ast_parser-1.0.6.dist-info/WHEEL
discord_markdown_ast_parser-1.0.6.dist-info/METADATA
discord_markdown_ast_parser-1.0.6.dist-info/RECORD
