Metadata-Version: 2.1
Name: discord-markdown-ast-parser
Version: 1.0.6
Summary: Markdown Parser for Discord messages that creates an abstract syntax tree
Home-page: https://github.com/w4rum/discord-markdown-ast-parser
License: MIT
Author: Tim Schmidt
Author-email: w4rum@khorne.faith
Requires-Python: >=3.8,<4.0
Classifier: License :: OSI Approved :: MIT License
Classifier: Programming Language :: Python :: 3
Classifier: Programming Language :: Python :: 3.8
Classifier: Programming Language :: Python :: 3.9
Project-URL: Documentation, https://github.com/w4rum/discord-markdown-ast-parser
Project-URL: Repository, https://github.com/w4rum/discord-markdown-ast-parser
